nti/__init__.py
nti/zodb/__init__.py
nti/zodb/activitylog.py
nti/zodb/btrees.py
nti/zodb/config_providers.py
nti/zodb/configure.zcml
nti/zodb/configure_activitylog.zcml
nti/zodb/configure_configprovider.zcml
nti/zodb/containers.py
nti/zodb/copy.py
nti/zodb/interfaces.py
nti/zodb/minmax.py
nti/zodb/persistentproperty.py
nti/zodb/schema.py
nti/zodb/tokenbucket.py
nti/zodb/urlproperty.py
nti/zodb/wref.py
nti/zodb/zlibstorage.py
nti/zodb/tests/__init__.py
nti/zodb/tests/prov_multi.zcml
nti/zodb/tests/test_activitylog.py
nti/zodb/tests/test_btrees.py
nti/zodb/tests/test_config_providers.py
nti/zodb/tests/test_containers.py
nti/zodb/tests/test_copy.py
nti/zodb/tests/test_main.py
nti/zodb/tests/test_minmax.py
nti/zodb/tests/test_persistentproperty.py
nti/zodb/tests/test_tokenbucket.py
nti/zodb/tests/test_wref.py
nti/zodb/tests/test_zlibstorage.py
nti.zodb-4.5.0.dist-info/AUTHORS
nti.zodb-4.5.0.dist-info/LICENSE
nti.zodb-4.5.0.dist-info/METADATA
nti.zodb-4.5.0.dist-info/WHEEL
nti.zodb-4.5.0.dist-info/top_level.txt
nti.zodb-4.5.0.dist-info/zip-safe
nti.zodb-4.5.0.dist-info/RECORD
