Metadata-Version: 2.1
Name: nti.zodb
Version: 4.5.0
Summary: Utilities for ZODB
Home-page: https://github.com/OpenNTI/nti.zodb
Author: Jason Madden
Author-email: jason@nextthought.com
License: Apache
Keywords: ZODB
Classifier: Intended Audience :: Developers
Classifier: Natural Language :: English
Classifier: Operating System :: OS Independent
Classifier: Framework :: ZODB
Classifier: License :: OSI Approved :: Apache Software License
Classifier: Programming Language :: Python :: 3
Classifier: Programming Language :: Python :: 3 :: Only
Classifier: Programming Language :: Python :: 3.10
Classifier: Programming Language :: Python :: 3.11
Classifier: Programming Language :: Python :: 3.12
Classifier: Programming Language :: Python :: 3.13
Classifier: Programming Language :: Python :: Implementation :: CPython
Classifier: Programming Language :: Python :: Implementation :: PyPy
Requires-Python: >=3.10
License-File: LICENSE
License-File: AUTHORS
Requires-Dist: nti.property
Requires-Dist: nti.schema
Requires-Dist: nti.wref
Requires-Dist: perfmetrics
Requires-Dist: persistent
Requires-Dist: repoze.zodbconn
Requires-Dist: transaction
Requires-Dist: zc.zlibstorage
Requires-Dist: ZODB
Requires-Dist: BTrees>=4.7.2
Requires-Dist: ZConfig
Requires-Dist: zope.component
Requires-Dist: zope.copy
Requires-Dist: zope.copypastemove
Requires-Dist: zope.deprecation
Requires-Dist: zope.event
Requires-Dist: zope.interface
Requires-Dist: zope.minmax
Requires-Dist: zope.processlifetime
Requires-Dist: zope.security
Requires-Dist: zope.site
Provides-Extra: docs
Requires-Dist: Sphinx; extra == "docs"
Requires-Dist: repoze.sphinx.autointerface; extra == "docs"
Requires-Dist: sphinx-rtd-theme; extra == "docs"
Provides-Extra: test
Requires-Dist: nti.testing; extra == "test"
Requires-Dist: zope.testrunner; extra == "test"
Requires-Dist: coverage; extra == "test"
